{
  "date": "2026-02-03T13:03:33.994992",
  "picks": [
    {
      "symbol": "META",
      "company_name": "Meta Platforms, Inc.",
      "current_price": 706.4099731445312,
      "change_1d": -1.408238221279658,
      "change_3d": 5.6345601029236425,
      "change_5d": 5.064249588732552,
      "change_1w": 9.076165066248725,
      "change_2w": 10.037853074471318,
      "change_1m": 8.609954077004279,
      "change_3m": 10.863253416492597,
      "volume": "14335200",
      "volume_ratio": 0.7849336456962445,
      "avg_volume": 18262945.0,
      "rsi": 64.44973220124365,
      "ma_5": 700.583984375,
      "ma_10": 669.8749938964844,
      "ma_20": 654.779995727539,
      "ma_50": 649.8893591308594,
      "ma_200": 643.8216857910156,
      "macd": 14.917423195658102,
      "macd_signal": 5.516290696053524,
      "macd_histogram": 9.401132499604579,
      "bb_upper": 725.0411712316145,
      "bb_lower": 584.5188202234635,
      "bb_position": 86.741469984371,
      "bb_width": 21.461002462668976,
      "stoch_k": 83.6157339590567,
      "stoch_d": 88.42134973502108,
      "williams_r": -26.104185316297745,
      "atr": 22.82143293108259,
      "atr_percent": 3.230621565193182,
      "obv_trend": 84375400.0,
      "support_distance": 15.06348681217724,
      "resistance_distance": 5.321276352900222,
      "recent_high": 744.0,
      "recent_low": 600.0,
      "score": 10,
      "recommendation": "STRONG BUY",
      "signals": [
        "\ud83c\udfaf Perfect MA stack",
        "Above 200-day MA",
        "RSI moderate 64.4",
        "\ud83d\ude80 MACD bullish",
        "\ud83d\udcc9 Stoch overbought",
        "Strong support level",
        "\ud83d\udcc8 Growth potential: 28.3% (confidence: 75%)"
      ],
      "buy_reasons": [
        "Weekly momentum +9.1%",
        "Perfect MA alignment (bullish)",
        "MACD bullish crossover"
      ],
      "sell_reasons": [
        "Stochastic overbought"
      ],
      "growth_potential": 28.32127635290022,
      "growth_confidence": 0.75,
      "growth_factors": [
        "Resistance upside: +5.3%",
        "RSI momentum: +5%",
        "MACD bullish trend: +6%",
        "Perfect MA alignment: +8%",
        "Momentum continuation: +4%"
      ],
      "has_recent_growth": "True",
      "meets_growth_requirement": "True",
      "market_cap": 1786903265280,
      "sector": "Communication Services",
      "pe_ratio": 30.034437,
      "forward_pe": 19.924774,
      "peg_ratio": 0,
      "price_to_book": 8.226792,
      "dividend_yield": 30.0,
      "ai_analysis": "Strong momentum with 9.1% recent growth. Healthy momentum with room to run.",
      "ai_score": 90
    },
    {
      "symbol": "INTC",
      "company_name": "Intel Corporation",
      "current_price": 48.810001373291016,
      "change_1d": 5.035506974648805,
      "change_3d": 0.061505934286481115,
      "change_5d": 14.874086714915538,
      "change_1w": -10.14359048690903,
      "change_2w": 10.780753181908501,
      "change_1m": 23.946165691729654,
      "change_3m": 23.569623729850672,
      "volume": "101045800",
      "volume_ratio": 0.6847185772684515,
      "avg_volume": 147572745.0,
      "rsi": 56.49794883023937,
      "ma_5": 47.33000030517578,
      "ma_10": 48.13400039672852,
      "ma_20": 46.26950035095215,
      "ma_50": 41.299400100708006,
      "ma_200": 40.482903388238725,
      "macd": 2.01020026614173,
      "macd_signal": 2.2146616600526166,
      "macd_histogram": -0.20446139391088636,
      "bb_upper": 54.436917944841795,
      "bb_lower": 38.102082757062504,
      "bb_position": 65.55265782075054,
      "bb_width": 35.30367750652217,
      "stoch_k": 47.141976543964724,
      "stoch_d": 47.439217608467175,
      "williams_r": -46.99673087867466,
      "atr": 3.742856434413365,
      "atr_percent": 7.668216203864866,
      "obv_trend": 152244900.0,
      "support_distance": 20.200779211096243,
      "resistance_distance": 11.862317020950512,
      "recent_high": 54.599998474121094,
      "recent_low": 38.95000076293945,
      "score": 11,
      "recommendation": "STRONG BUY",
      "signals": [
        "\ud83d\ude80 Daily surge +5.0%",
        "\ud83d\udcc8 Above key MAs",
        "Above 200-day MA",
        "RSI moderate 56.5",
        "\ud83d\udcc9 MACD bearish",
        "High volatility 7.7%",
        "Strong support level",
        "\u2728 Golden cross"
      ],
      "buy_reasons": [
        "Strong daily momentum +5.0%",
        "Strong 5-day trend +14.9%",
        "Strong monthly trend +23.9%",
        "Golden cross formation"
      ],
      "sell_reasons": [
        "Weekly decline -10.1%",
        "MACD bearish crossover"
      ],
      "growth_potential": 20.862317020950513,
      "growth_confidence": 0.4,
      "growth_factors": [
        "Resistance upside: +11.9%",
        "RSI momentum: +5%",
        "Good MA trend: +4%"
      ],
      "has_recent_growth": "True",
      "meets_growth_requirement": "True",
      "market_cap": 243814662144,
      "sector": "Technology",
      "pe_ratio": 0,
      "forward_pe": 49.218513,
      "peg_ratio": 0,
      "price_to_book": 2.1329312,
      "dividend_yield": 0,
      "ai_analysis": "Strong momentum with 23.9% recent growth. Healthy momentum with room to run.",
      "ai_score": 90
    },
    {
      "symbol": "LRCX",
      "company_name": "Lam Research Corporation",
      "current_price": 237.5,
      "change_1d": 1.7304862374497836,
      "change_3d": -0.868186749794521,
      "change_5d": 6.564367211081905,
      "change_1w": 7.6121446688092576,
      "change_2w": 7.758623673804189,
      "change_1m": 28.336757339901446,
      "change_3m": 47.53844603668157,
      "volume": "13285500",
      "volume_ratio": 0.9321398276395544,
      "avg_volume": 14252690.0,
      "rsi": 59.319821192387835,
      "ma_5": 239.4340026855469,
      "ma_10": 230.9480010986328,
      "ma_20": 220.88000106811523,
      "ma_50": 186.1127770996094,
      "ma_200": 180.40974524713332,
      "macd": 14.760647312511423,
      "macd_signal": 14.323367821906897,
      "macd_histogram": 0.4372794906045261,
      "bb_upper": 248.82720404088934,
      "bb_lower": 192.93279809534113,
      "bb_position": 79.73463739479728,
      "bb_width": 25.30532672729906,
      "stoch_k": 73.65907900996683,
      "stoch_d": 82.9722207621899,
      "williams_r": -31.74988259226832,
      "atr": 12.060003008161273,
      "atr_percent": 5.077896003436325,
      "obv_trend": 40335700.0,
      "support_distance": 19.94947574013158,
      "resistance_distance": 6.05052425986842,
      "recent_high": 251.8699951171875,
      "recent_low": 190.1199951171875,
      "score": 13,
      "recommendation": "STRONG BUY",
      "signals": [
        "\ud83d\udcc8 Above key MAs",
        "Above 200-day MA",
        "RSI moderate 59.3",
        "\ud83d\ude80 MACD bullish",
        "High volatility 5.1%",
        "Strong support level",
        "\u2728 Golden cross",
        "\ud83d\udcc8 Growth potential: 25.1% (confidence: 70%)"
      ],
      "buy_reasons": [
        "Weekly momentum +7.6%",
        "MACD bullish crossover",
        "Strong monthly trend +28.3%",
        "Golden cross formation"
      ],
      "sell_reasons": [],
      "growth_potential": 25.05052425986842,
      "growth_confidence": 0.7,
      "growth_factors": [
        "Resistance upside: +6.1%",
        "RSI momentum: +5%",
        "MACD bullish trend: +6%",
        "Good MA trend: +4%",
        "Momentum continuation: +4%"
      ],
      "has_recent_growth": "True",
      "meets_growth_requirement": "True",
      "market_cap": 298307125248,
      "sector": "Technology",
      "pe_ratio": 48.767967,
      "forward_pe": 35.097416,
      "peg_ratio": 0,
      "price_to_book": 29.288445,
      "dividend_yield": 44.0,
      "ai_analysis": "Strong momentum with 28.3% recent growth. Healthy momentum with room to run.",
      "ai_score": 90
    },
    {
      "symbol": "ASML",
      "company_name": "ASML Holding N.V.",
      "current_price": 1441.3900146484375,
      "change_1d": 1.2923411558986295,
      "change_3d": 1.2980329275504157,
      "change_5d": 1.9839416667393612,
      "change_1w": 3.3254490787410393,
      "change_2w": 12.500490670776488,
      "change_1m": 23.85416301732614,
      "change_3m": 35.110898485008505,
      "volume": "1765200",
      "volume_ratio": 0.7583353739480094,
      "avg_volume": 2327730.0,
      "rsi": 70.03202911415636,
      "ma_5": 1439.41201171875,
      "ma_10": 1408.0609985351562,
      "ma_20": 1337.6469848632812,
      "ma_50": 1176.6753881835937,
      "ma_200": 1147.9045045914188,
      "macd": 79.87288192536812,
      "macd_signal": 75.51759815092483,
      "macd_histogram": 4.3552837744432935,
      "bb_upper": 1507.1054316096552,
      "bb_lower": 1168.1885381169072,
      "bb_position": 80.61016779542037,
      "bb_width": 25.336796428946318,
      "stoch_k": 78.55823038561506,
      "stoch_d": 80.86805260307916,
      "williams_r": -21.360604014314454,
      "atr": 50.58070591517857,
      "atr_percent": 3.5091616704112845,
      "obv_trend": 5338800.0,
      "support_distance": 18.41208916055711,
      "resistance_distance": 3.613870312055514,
      "recent_high": 1493.47998046875,
      "recent_low": 1176.0,
      "score": 12,
      "recommendation": "STRONG BUY",
      "signals": [
        "\ud83c\udfaf Perfect MA stack",
        "Above 200-day MA",
        "\u26a0\ufe0f RSI overbought 70.0",
        "\ud83d\ude80 MACD bullish",
        "Strong support level",
        "\u2728 Golden cross",
        "\ud83d\udcc8 Growth potential: 21.6% (confidence: 60%)"
      ],
      "buy_reasons": [
        "Perfect MA alignment (bullish)",
        "MACD bullish crossover",
        "Strong monthly trend +23.9%",
        "Golden cross formation"
      ],
      "sell_reasons": [
        "Overbought RSI 70.0"
      ],
      "growth_potential": 21.613870312055514,
      "growth_confidence": 0.6,
      "growth_factors": [
        "Resistance upside: +3.6%",
        "MACD bullish trend: +6%",
        "Perfect MA alignment: +8%",
        "Momentum continuation: +4%"
      ],
      "has_recent_growth": "True",
      "meets_growth_requirement": "True",
      "market_cap": 559472181248,
      "sector": "Technology",
      "pe_ratio": 49.261448,
      "forward_pe": 33.135853,
      "peg_ratio": 0,
      "price_to_book": 23.974285,
      "dividend_yield": 61.0,
      "ai_analysis": "Strong momentum with 23.9% recent growth. High growth potential of 21.6%.",
      "ai_score": 85
    },
    {
      "symbol": "TXN",
      "company_name": "Texas Instruments Incorporated",
      "current_price": 225.00999450683594,
      "change_1d": 4.388768880140816,
      "change_3d": 4.7687872565389835,
      "change_5d": 15.203569139539688,
      "change_1w": 16.14887214432583,
      "change_2w": 19.785625940962127,
      "change_1m": 27.579247698621256,
      "change_3m": 40.26922169240365,
      "volume": "11189900",
      "volume_ratio": 1.2547037796186742,
      "avg_volume": 8918360.0,
      "rsi": 81.96511722823409,
      "ma_5": 213.6466064453125,
      "ma_10": 203.0839859008789,
      "ma_20": 195.20512924194335,
      "ma_50": 181.66394622802736,
      "ma_200": 177.32762884324598,
      "macd": 9.823662292747258,
      "macd_signal": 6.779172751012452,
      "macd_histogram": 3.044489541734806,
      "bb_upper": 220.55686641876733,
      "bb_lower": 169.85339206511938,
      "bb_position": 108.7826882572362,
      "bb_width": 25.974458022977704,
      "stoch_k": 92.00000968241493,
      "stoch_d": 91.64642873355474,
      "williams_r": -0.6404423577572707,
      "atr": 6.5399780157001715,
      "atr_percent": 2.906527787814102,
      "obv_trend": 63589300.0,
      "support_distance": 21.895525344656445,
      "resistance_distance": 0.11110617577140772,
      "recent_high": 225.25999450683594,
      "recent_low": 175.7428741315816,
      "score": 10,
      "recommendation": "STRONG BUY",
      "signals": [
        "\ud83d\udcc8 Daily gain +4.4%",
        "\ud83c\udfaf Perfect MA stack",
        "Above 200-day MA",
        "\ud83d\udd34 RSI extreme 82.0",
        "\ud83d\ude80 MACD bullish",
        "\u26a0\ufe0f BB overbought",
        "\ud83d\udcc9 Stoch overbought",
        "Strong support level",
        "\u2728 Golden cross",
        "\ud83d\udcc8 Growth potential: 14.1% (confidence: 50%)"
      ],
      "buy_reasons": [
        "Strong 5-day trend +15.2%",
        "Weekly momentum +16.1%",
        "Perfect MA alignment (bullish)",
        "MACD bullish crossover",
        "Strong monthly trend +27.6%",
        "Golden cross formation"
      ],
      "sell_reasons": [
        "Extremely overbought RSI 82.0",
        "Near Bollinger upper band",
        "Stochastic overbought",
        "Williams %R overbought"
      ],
      "growth_potential": 14.111106175771408,
      "growth_confidence": 0.5,
      "growth_factors": [
        "Resistance upside: +0.1%",
        "MACD bullish trend: +6%",
        "Perfect MA alignment: +8%"
      ],
      "has_recent_growth": "True",
      "meets_growth_requirement": "True",
      "market_cap": 204449267712,
      "sector": "Technology",
      "pe_ratio": 41.28624,
      "forward_pe": 28.70538,
      "peg_ratio": 0,
      "price_to_book": 12.540965,
      "dividend_yield": 252.0,
      "ai_analysis": "Strong momentum with 27.6% recent growth. High growth potential of 14.1%.",
      "ai_score": 84
    },
    {
      "symbol": "BIIB",
      "company_name": "Biogen Inc.",
      "current_price": 179.08999633789062,
      "change_1d": -0.44471791343162775,
      "change_3d": 2.4366495808611517,
      "change_5d": 3.4484758485938856,
      "change_1w": 3.0437245070458645,
      "change_2w": -3.5231419344359534,
      "change_1m": 0.7141991684638205,
      "change_3m": 18.258051671111435,
      "volume": "1288800",
      "volume_ratio": 0.8200429491768074,
      "avg_volume": 1571625.0,
      "rsi": 42.19569840784279,
      "ma_5": 176.8219970703125,
      "ma_10": 174.06199798583984,
      "ma_20": 176.2309997558594,
      "ma_50": 176.3056005859375,
      "ma_200": 172.98096786006803,
      "macd": 0.16705260246436637,
      "macd_signal": -0.44317240590201534,
      "macd_histogram": 0.6102250083663817,
      "bb_upper": 190.1256846771544,
      "bb_lower": 162.33631483456438,
      "bb_position": 60.28809432608845,
      "bb_width": 15.7687182624441,
      "stoch_k": 65.27465147781474,
      "stoch_d": 57.2901190069038,
      "williams_r": -27.850574408619217,
      "atr": 5.278569902692523,
      "atr_percent": 2.9474398406560907,
      "obv_trend": 5640700.0,
      "support_distance": 10.45842655119665,
      "resistance_distance": 6.203585257431258,
      "recent_high": 190.1999969482422,
      "recent_low": 160.36000061035156,
      "score": 9,
      "recommendation": "STRONG BUY",
      "signals": [
        "Above 20-day MA",
        "Above 200-day MA",
        "RSI healthy 42.2",
        "\ud83d\ude80 MACD bullish",
        "Strong support level",
        "\ud83d\udcc8 Growth potential: 28.2% (confidence: 75%)"
      ],
      "buy_reasons": [
        "MACD bullish crossover"
      ],
      "sell_reasons": [],
      "growth_potential": 28.203585257431257,
      "growth_confidence": 0.75,
      "growth_factors": [
        "Resistance upside: +6.2%",
        "RSI oversold bounce: +8%",
        "MACD bullish trend: +6%",
        "Good MA trend: +4%",
        "Momentum continuation: +4%"
      ],
      "has_recent_growth": "False",
      "meets_growth_requirement": true,
      "market_cap": 26272909312,
      "sector": "Healthcare",
      "pe_ratio": 16.310566,
      "forward_pe": 11.9766445,
      "peg_ratio": 0,
      "price_to_book": 1.4429476,
      "dividend_yield": 0,
      "ai_analysis": "Strong momentum with 3.0% recent growth. High growth potential of 28.2%.",
      "ai_score": 84
    },
    {
      "symbol": "WFC",
      "company_name": "Wells Fargo & Company",
      "current_price": 92.2699966430664,
      "change_1d": 1.9670668817747345,
      "change_3d": 4.81653745605493,
      "change_5d": 4.792723958030966,
      "change_1w": 4.804629354329131,
      "change_2w": -2.8327742916397147,
      "change_1m": -3.0777315116603923,
      "change_3m": 6.248697589508326,
      "volume": "13834400",
      "volume_ratio": 0.780515766425252,
      "avg_volume": 17724690.0,
      "rsi": 42.84954069497668,
      "ma_5": 90.02799835205079,
      "ma_10": 88.59700012207031,
      "ma_20": 90.98449935913087,
      "ma_50": 90.50679977416992,
      "ma_200": 89.55746681459489,
      "macd": -0.5687087417817196,
      "macd_signal": -0.7266488950435586,
      "macd_histogram": 0.15794015326183897,
      "bb_upper": 98.14146357198524,
      "bb_lower": 83.82753514627649,
      "bb_position": 58.980744109539515,
      "bb_width": 15.732271460009152,
      "stoch_k": 51.27346723809009,
      "stoch_d": 38.95100572354499,
      "williams_r": -35.80249917583711,
      "atr": 2.291429247174944,
      "atr_percent": 2.4833958280490873,
      "obv_trend": 15615900.0,
      "support_distance": 6.762759391775088,
      "resistance_distance": 5.9499357243952025,
      "recent_high": 97.76000213623047,
      "recent_low": 86.02999877929688,
      "score": 9,
      "recommendation": "STRONG BUY",
      "signals": [
        "\ud83d\udcc8 Above key MAs",
        "Above 200-day MA",
        "RSI healthy 42.8",
        "\ud83d\ude80 MACD bullish",
        "\ud83d\udcc8 Growth potential: 21.9% (confidence: 55%)"
      ],
      "buy_reasons": [
        "MACD bullish crossover"
      ],
      "sell_reasons": [],
      "growth_potential": 21.949935724395203,
      "growth_confidence": 0.5499999999999999,
      "growth_factors": [
        "Resistance upside: +5.9%",
        "RSI oversold bounce: +8%",
        "Good MA trend: +4%",
        "Momentum continuation: +4%"
      ],
      "has_recent_growth": "False",
      "meets_growth_requirement": true,
      "market_cap": 289643331584,
      "sector": "Financial Services",
      "pe_ratio": 14.739615,
      "forward_pe": 11.715933,
      "peg_ratio": 0,
      "price_to_book": 1.7345941,
      "dividend_yield": 195.0,
      "ai_analysis": "Strong momentum with 4.8% recent growth. High growth potential of 21.9%.",
      "ai_score": 84
    },
    {
      "symbol": "BAC",
      "company_name": "Bank of America Corporation",
      "current_price": 54.029998779296875,
      "change_1d": 1.5601466249143754,
      "change_3d": 4.28488196711438,
      "change_5d": 3.8638952399955677,
      "change_1w": 3.0123889292177664,
      "change_2w": -2.1018298174965566,
      "change_1m": -3.431638887330207,
      "change_3m": 1.4017479860531108,
      "volume": "34614700",
      "volume_ratio": 0.8636956012398999,
      "avg_volume": 40077430.0,
      "rsi": 42.96116089099171,
      "ma_5": 52.85800018310547,
      "ma_10": 52.46500015258789,
      "ma_20": 53.711499977111814,
      "ma_50": 53.935597610473636,
      "ma_200": 53.69827233591387,
      "macd": -0.4836037113999154,
      "macd_signal": -0.539722841103607,
      "macd_histogram": 0.056119129703691595,
      "bb_upper": 57.372677076108396,
      "bb_lower": 50.05032287811523,
      "bb_position": 54.34967762515984,
      "bb_width": 13.63274941327919,
      "stoch_k": 47.63245840264983,
      "stoch_d": 31.999959756957065,
      "williams_r": -35.39197155558133,
      "atr": 1.1050000871930803,
      "atr_percent": 2.0451603038282733,
      "obv_trend": 83892500.0,
      "support_distance": 5.034235549618601,
      "resistance_distance": 6.514900124544256,
      "recent_high": 57.54999923706055,
      "recent_low": 51.310001373291016,
      "score": 8,
      "recommendation": "STRONG BUY",
      "signals": [
        "Above 20-day MA",
        "Above 200-day MA",
        "RSI healthy 43.0",
        "\ud83d\ude80 MACD bullish",
        "\ud83d\udcc8 Growth potential: 22.5% (confidence: 55%)"
      ],
      "buy_reasons": [
        "MACD bullish crossover"
      ],
      "sell_reasons": [],
      "growth_potential": 22.514900124544255,
      "growth_confidence": 0.5499999999999999,
      "growth_factors": [
        "Resistance upside: +6.5%",
        "RSI oversold bounce: +8%",
        "Good MA trend: +4%",
        "Momentum continuation: +4%"
      ],
      "has_recent_growth": "False",
      "meets_growth_requirement": true,
      "market_cap": 394553851904,
      "sector": "Financial Services",
      "pe_ratio": 14.181102,
      "forward_pe": 10.901342,
      "peg_ratio": 0,
      "price_to_book": 1.4055305,
      "dividend_yield": 206.99999999999997,
      "ai_analysis": "Strong momentum with 3.0% recent growth. High growth potential of 22.5%.",
      "ai_score": 80
    },
    {
      "symbol": "MU",
      "company_name": "Micron Technology, Inc.",
      "current_price": 437.79998779296875,
      "change_1d": 5.524484824625437,
      "change_3d": 0.5789351729321253,
      "change_5d": 12.518952405236798,
      "change_1w": 10.116203677015967,
      "change_2w": 26.579348880678005,
      "change_1m": 38.79905178980431,
      "change_3m": 86.61135467972606,
      "volume": "37477800",
      "volume_ratio": 1.0064287125079605,
      "avg_volume": 37238405.0,
      "rsi": 75.54888733209053,
      "ma_5": 426.797998046875,
      "ma_10": 407.44199523925784,
      "ma_20": 372.9194961547852,
      "ma_50": 299.3697164916992,
      "ma_200": 287.5379175986013,
      "macd": 36.97481272728237,
      "macd_signal": 33.064774057269155,
      "macd_histogram": 3.910038670013215,
      "bb_upper": 453.1808033700747,
      "bb_lower": 292.65818893949563,
      "bb_position": 90.41828739728277,
      "bb_width": 43.04484374932011,
      "stoch_k": 82.22026919640984,
      "stoch_d": 87.43815744162453,
      "williams_r": -13.904174316039397,
      "atr": 24.406426565987722,
      "atr_percent": 5.574789229443578,
      "obv_trend": 210599100.0,
      "support_distance": 29.294199080847882,
      "resistance_distance": 4.042944883635175,
      "recent_high": 455.5,
      "recent_low": 309.54998779296875,
      "score": 13,
      "recommendation": "STRONG BUY",
      "signals": [
        "\ud83d\ude80 Daily surge +5.5%",
        "\ud83c\udfaf Perfect MA stack",
        "Above 200-day MA",
        "\u26a0\ufe0f RSI overbought 75.5",
        "\ud83d\ude80 MACD bullish",
        "\u26a0\ufe0f BB overbought",
        "\ud83d\udcc9 Stoch overbought",
        "High volatility 5.6%",
        "Strong support level",
        "\u2728 Golden cross",
        "\ud83d\udcc8 Growth potential: 18.0% (confidence: 50%)"
      ],
      "buy_reasons": [
        "Strong daily momentum +5.5%",
        "Strong 5-day trend +12.5%",
        "Weekly momentum +10.1%",
        "Perfect MA alignment (bullish)",
        "MACD bullish crossover",
        "Strong monthly trend +38.8%",
        "Golden cross formation"
      ],
      "sell_reasons": [
        "Overbought RSI 75.5",
        "Near Bollinger upper band",
        "Stochastic overbought",
        "Williams %R overbought"
      ],
      "growth_potential": 18.042944883635176,
      "growth_confidence": 0.5,
      "growth_factors": [
        "Resistance upside: +4.0%",
        "MACD bullish trend: +6%",
        "Perfect MA alignment: +8%"
      ],
      "has_recent_growth": "True",
      "meets_growth_requirement": "True",
      "market_cap": 492747948032,
      "sector": "Technology",
      "pe_ratio": 41.655563,
      "forward_pe": 10.054433,
      "peg_ratio": 0,
      "price_to_book": 8.382797,
      "dividend_yield": 11.0,
      "ai_analysis": "Strong momentum with 38.8% recent growth. High growth potential of 18.0%.",
      "ai_score": 80
    },
    {
      "symbol": "MA",
      "company_name": "Mastercard Incorporated",
      "current_price": 555.3699951171875,
      "change_1d": 3.0772690224394466,
      "change_3d": 6.521280533675106,
      "change_5d": 5.311364256609692,
      "change_1w": 4.224376080852398,
      "change_2w": -1.9266146809439864,
      "change_1m": -1.2298745919124525,
      "change_3m": 2.230269553774192,
      "volume": "4602200",
      "volume_ratio": 1.0511517742839882,
      "avg_volume": 4378245.0,
      "rsi": 45.049447366001345,
      "ma_5": 535.933984375,
      "ma_10": 532.3939880371094,
      "ma_20": 547.2573455810547,
      "ma_50": 552.4319458007812,
      "ma_200": 551.6993211315524,
      "macd": -6.332325458104606,
      "macd_signal": -7.215282466550998,
      "macd_histogram": 0.8829570084463922,
      "bb_upper": 588.336229813429,
      "bb_lower": 506.17846134868034,
      "bb_position": 59.87447649532219,
      "bb_width": 15.012638775550286,
      "stoch_k": 57.64970936548438,
      "stoch_d": 33.9022367315639,
      "williams_r": -8.80043690857178,
      "atr": 12.770721435546875,
      "atr_percent": 2.2994979109111124,
      "obv_trend": 7429800.0,
      "support_distance": 6.680226859952906,
      "resistance_distance": 6.016816685254864,
      "recent_high": 588.7855896482976,
      "recent_low": 518.27001953125,
      "score": 7,
      "recommendation": "BUY",
      "signals": [
        "\ud83d\udcc8 Daily gain +3.1%",
        "Above 20-day MA",
        "Above 200-day MA",
        "RSI neutral 45.0",
        "\ud83d\ude80 MACD bullish",
        "\ud83d\udcc8 Growth potential: 19.0% (confidence: 50%)"
      ],
      "buy_reasons": [
        "MACD bullish crossover"
      ],
      "sell_reasons": [
        "Williams %R overbought"
      ],
      "growth_potential": 19.016816685254863,
      "growth_confidence": 0.5,
      "growth_factors": [
        "Resistance upside: +6.0%",
        "RSI momentum: +5%",
        "Good MA trend: +4%",
        "Momentum continuation: +4%"
      ],
      "has_recent_growth": "False",
      "meets_growth_requirement": true,
      "market_cap": 496188489728,
      "sector": "Financial Services",
      "pe_ratio": 33.6792,
      "forward_pe": 24.605707,
      "peg_ratio": 0,
      "price_to_book": 64.17494,
      "dividend_yield": 63.0,
      "ai_analysis": "Strong momentum with 4.2% recent growth. High growth potential of 19.0%.",
      "ai_score": 78
    }
  ]
}