{
  "date": "2026-05-01T13:20:44.502879",
  "picks": [
    {
      "symbol": "AAPL",
      "company_name": "Apple Inc.",
      "current_price": 271.3500061035156,
      "change_1d": 0.43675930604225877,
      "change_3d": 1.397563976187142,
      "change_5d": -0.7607016889079767,
      "change_1w": 1.9461218072890196,
      "change_2w": 4.173063060012707,
      "change_1m": 6.149513328026413,
      "change_3m": 0.590310424318708,
      "volume": "90134300",
      "volume_ratio": 2.0821881036567422,
      "avg_volume": 43288260.0,
      "rsi": 61.63562856724718,
      "ma_5": 270.17999877929685,
      "ma_10": 270.69500122070315,
      "ma_20": 265.14799880981445,
      "ma_50": 260.8273992919922,
      "ma_200": 262.57482614824846,
      "macd": 3.6664684232250124,
      "macd_signal": 3.2077670119636466,
      "macd_histogram": 0.4587014112613659,
      "bb_upper": 277.9688854245543,
      "bb_lower": 252.3271121950746,
      "bb_position": 74.18712324688566,
      "bb_width": 9.67073986776421,
      "stoch_k": 73.65579300928289,
      "stoch_d": 71.3096324717089,
      "williams_r": -24.04340629255538,
      "atr": 5.909997122628348,
      "atr_percent": 2.1779977850355308,
      "obv_trend": 83510600.0,
      "support_distance": 9.452739479758248,
      "resistance_distance": 1.713651664599734,
      "recent_high": 276.0,
      "recent_low": 245.6999969482422,
      "score": 9,
      "recommendation": "STRONG BUY",
      "signals": [
        "\ud83d\udcc8 Above key MAs",
        "Above 200-day MA",
        "RSI moderate 61.6",
        "\ud83d\ude80 MACD bullish",
        "BB squeeze (breakout pending)",
        "\ud83d\udd0a High volume 2.1x",
        "Near resistance",
        "\ud83d\udcc8 Growth potential: 21.7% (confidence: 75%)"
      ],
      "buy_reasons": [
        "MACD bullish crossover"
      ],
      "sell_reasons": [],
      "growth_potential": 21.713651664599734,
      "growth_confidence": 0.75,
      "growth_factors": [
        "Resistance upside: +1.7%",
        "RSI momentum: +5%",
        "MACD bullish trend: +6%",
        "Good MA trend: +4%",
        "High volume breakout: +5%"
      ],
      "has_recent_growth": "False",
      "meets_growth_requirement": true,
      "market_cap": 3983727394816,
      "sector": "Technology",
      "pe_ratio": 34.348103,
      "forward_pe": 28.876884,
      "peg_ratio": 0,
      "price_to_book": 45.24008,
      "dividend_yield": 38.0,
      "ai_analysis": "Strong momentum with 6.1% recent growth. Healthy momentum with room to run.",
      "ai_score": 96
    },
    {
      "symbol": "MSFT",
      "company_name": "Microsoft Corporation",
      "current_price": 407.7799987792969,
      "change_1d": -3.9296972651300033,
      "change_3d": -4.011112530280876,
      "change_5d": -1.9170177319791042,
      "change_1w": -3.861751400742866,
      "change_2w": 9.952275500326348,
      "change_1m": 10.398788252934105,
      "change_3m": -3.4625192430012115,
      "volume": "70783800",
      "volume_ratio": 2.060734846311292,
      "avg_volume": 34348815.0,
      "rsi": 64.9276037746701,
      "ma_5": 422.1859985351563,
      "ma_10": 422.4620025634766,
      "ma_20": 403.5240005493164,
      "ma_50": 395.7907995605469,
      "ma_200": 397.62709045410156,
      "macd": 9.751451290639295,
      "macd_signal": 8.756372457874065,
      "macd_histogram": 0.9950788327652305,
      "bb_upper": 450.5808742594879,
      "bb_lower": 356.46712683914484,
      "bb_position": 54.522185490045146,
      "bb_width": 23.322961531959994,
      "stoch_k": 79.15268215833048,
      "stoch_d": 85.4912943186347,
      "williams_r": -41.35290975846427,
      "atr": 12.670713152204241,
      "atr_percent": 3.1072424322268004,
      "obv_trend": -24772800.0,
      "support_distance": 10.699397962975228,
      "resistance_distance": 6.3563719420586615,
      "recent_high": 433.70001220703125,
      "recent_low": 364.1499938964844,
      "score": 8,
      "recommendation": "STRONG BUY",
      "signals": [
        "\ud83d\udcc9 Daily loss -3.9%",
        "\ud83d\udcc8 Above key MAs",
        "Above 200-day MA",
        "RSI moderate 64.9",
        "\ud83d\ude80 MACD bullish",
        "\ud83d\udd0a High volume 2.1x",
        "Strong support level",
        "\ud83d\udcc8 Growth potential: 26.4% (confidence: 75%)"
      ],
      "buy_reasons": [
        "MACD bullish crossover"
      ],
      "sell_reasons": [],
      "growth_potential": 26.35637194205866,
      "growth_confidence": 0.75,
      "growth_factors": [
        "Resistance upside: +6.4%",
        "RSI momentum: +5%",
        "MACD bullish trend: +6%",
        "Good MA trend: +4%",
        "High volume breakout: +5%"
      ],
      "has_recent_growth": "True",
      "meets_growth_requirement": "True",
      "market_cap": 3029167243264,
      "sector": "Technology",
      "pe_ratio": 24.27262,
      "forward_pe": 21.130917,
      "peg_ratio": 0,
      "price_to_book": 7.750261,
      "dividend_yield": 89.0,
      "ai_analysis": "Strong momentum with 10.4% recent growth. Healthy momentum with room to run.",
      "ai_score": 92
    },
    {
      "symbol": "GOOGL",
      "company_name": "Alphabet Inc.",
      "current_price": 384.79998779296875,
      "change_1d": 9.961703465838957,
      "change_3d": 9.836156823454058,
      "change_5d": 13.547160187696289,
      "change_1w": 15.802455053639724,
      "change_2w": 21.296179434591718,
      "change_1m": 29.392369897780124,
      "change_3m": 12.040168073678315,
      "volume": "71949900",
      "volume_ratio": 2.731111886730251,
      "avg_volume": 26344545.0,
      "rsi": 87.31773560275616,
      "ma_5": 355.85199584960935,
      "ma_10": 346.88600158691406,
      "ma_20": 332.52449798583984,
      "ma_50": 313.8031561279297,
      "ma_200": 315.0311820737777,
      "macd": 14.475216079760457,
      "macd_signal": 10.684480284558171,
      "macd_histogram": 3.790735795202286,
      "bb_upper": 373.4342257106497,
      "bb_lower": 291.61477026103,
      "bb_position": 113.89127074955606,
      "bb_width": 24.60554213154661,
      "stoch_k": 91.98032766065127,
      "stoch_d": 92.21920133518643,
      "williams_r": -1.4779147606731302,
      "atr": 9.775717599051339,
      "atr_percent": 2.5404672321119977,
      "obv_trend": 94239800.0,
      "support_distance": 24.77910047056394,
      "resistance_distance": 0.2702724994579323,
      "recent_high": 385.8399963378906,
      "recent_low": 289.45001220703125,
      "score": 12,
      "recommendation": "STRONG BUY",
      "signals": [
        "\ud83d\ude80 Daily surge +10.0%",
        "\ud83c\udfaf Perfect MA stack",
        "Above 200-day MA",
        "\ud83d\udd34 RSI extreme 87.3",
        "\ud83d\ude80 MACD bullish",
        "\u26a0\ufe0f BB overbought",
        "\ud83d\udcc9 Stoch overbought",
        "\ud83d\udd0a High volume 2.7x",
        "Strong support level",
        "\ud83d\udcc8 Growth potential: 19.3% (confidence: 65%)"
      ],
      "buy_reasons": [
        "Strong daily momentum +10.0%",
        "Strong 5-day trend +13.5%",
        "Weekly momentum +15.8%",
        "Perfect MA alignment (bullish)",
        "MACD bullish crossover",
        "Strong monthly trend +29.4%"
      ],
      "sell_reasons": [
        "Extremely overbought RSI 87.3",
        "Near Bollinger upper band",
        "Stochastic overbought",
        "Williams %R overbought"
      ],
      "growth_potential": 19.27027249945793,
      "growth_confidence": 0.65,
      "growth_factors": [
        "Resistance upside: +0.3%",
        "MACD bullish trend: +6%",
        "Perfect MA alignment: +8%",
        "High volume breakout: +5%"
      ],
      "has_recent_growth": "True",
      "meets_growth_requirement": "True",
      "market_cap": 4662022373376,
      "sector": "Communication Services",
      "pe_ratio": 29.329268,
      "forward_pe": 28.444496,
      "peg_ratio": 0,
      "price_to_book": 11.20135,
      "dividend_yield": 24.0,
      "ai_analysis": "Strong momentum with 29.4% recent growth. Strong volume confirms the move.",
      "ai_score": 90
    },
    {
      "symbol": "QCOM",
      "company_name": "QUALCOMM Incorporated",
      "current_price": 179.5800018310547,
      "change_1d": 15.115385789137619,
      "change_3d": 19.512849990743785,
      "change_5d": 34.064954029408284,
      "change_1w": 32.47270954946275,
      "change_2w": 40.23114575563536,
      "change_1m": 41.090511905524025,
      "change_3m": 18.420250312528424,
      "volume": "61082400",
      "volume_ratio": 3.682870741621919,
      "avg_volume": 16585540.0,
      "rsi": 92.7906817000311,
      "ma_5": 156.93800048828126,
      "ma_10": 146.3990005493164,
      "ma_20": 137.77550086975097,
      "ma_50": 135.80179626464843,
      "ma_200": 136.88108456519342,
      "macd": 7.398391796103624,
      "macd_signal": 3.228837635012032,
      "macd_histogram": 4.169554161091592,
      "bb_upper": 164.47736539860543,
      "bb_lower": 111.0736363408965,
      "bb_position": 128.28011582511235,
      "bb_width": 38.761411659243606,
      "stoch_k": 80.52675364656706,
      "stoch_d": 77.06606112198892,
      "williams_r": -12.096636640208084,
      "atr": 7.499998365129743,
      "atr_percent": 4.176410674160475,
      "obv_trend": 142272900.0,
      "support_distance": 32.0692746297356,
      "resistance_distance": 4.070607798228474,
      "recent_high": 186.88999938964844,
      "recent_low": 121.98999786376953,
      "score": 14,
      "recommendation": "STRONG BUY",
      "signals": [
        "\ud83d\ude80 Daily surge +15.1%",
        "\ud83c\udfaf Perfect MA stack",
        "Above 200-day MA",
        "\ud83d\udd34 RSI extreme 92.8",
        "\ud83d\ude80 MACD bullish",
        "\u26a0\ufe0f BB overbought",
        "\ud83d\udd0a High volume 3.7x",
        "Strong support level",
        "\ud83d\udcc8 Growth potential: 23.1% (confidence: 65%)"
      ],
      "buy_reasons": [
        "Strong daily momentum +15.1%",
        "Strong 5-day trend +34.1%",
        "Weekly momentum +32.5%",
        "Perfect MA alignment (bullish)",
        "MACD bullish crossover",
        "Strong monthly trend +41.1%"
      ],
      "sell_reasons": [
        "Extremely overbought RSI 92.8",
        "Near Bollinger upper band",
        "Williams %R overbought"
      ],
      "growth_potential": 23.070607798228473,
      "growth_confidence": 0.65,
      "growth_factors": [
        "Resistance upside: +4.1%",
        "MACD bullish trend: +6%",
        "Perfect MA alignment: +8%",
        "High volume breakout: +5%"
      ],
      "has_recent_growth": "True",
      "meets_growth_requirement": "True",
      "market_cap": 189277323264,
      "sector": "Technology",
      "pe_ratio": 19.309677,
      "forward_pe": 16.83333,
      "peg_ratio": 0.65,
      "price_to_book": 8.359168,
      "dividend_yield": 204.99999999999997,
      "ai_analysis": "Strong momentum with 41.1% recent growth. Strong volume confirms the move.",
      "ai_score": 90
    },
    {
      "symbol": "TSM",
      "company_name": "Taiwan Semiconductor Manufacturing Company Limited",
      "current_price": 396.05999755859375,
      "change_1d": 0.5662369708658359,
      "change_3d": -2.202581160983649,
      "change_5d": 3.5018015387666788,
      "change_1w": 7.601611608088551,
      "change_2w": 6.869938217962863,
      "change_1m": 15.979972732660682,
      "change_3m": 16.351071080145747,
      "volume": "12762200",
      "volume_ratio": 0.9500813124942072,
      "avg_volume": 13432745.0,
      "rsi": 62.2450839746689,
      "ma_5": 397.9339965820312,
      "ma_10": 386.45899658203126,
      "ma_20": 374.030500793457,
      "ma_50": 359.1627471923828,
      "ma_200": 357.7580354752079,
      "macd": 12.433500209369583,
      "macd_signal": 10.102165885236325,
      "macd_histogram": 2.331334324133259,
      "bb_upper": 411.73233467539575,
      "bb_lower": 336.32866691151827,
      "bb_position": 79.21541805382853,
      "bb_width": 20.15976440528738,
      "stoch_k": 62.14395695523449,
      "stoch_d": 69.11029193371262,
      "williams_r": -34.17979289910704,
      "atr": 12.941434587751116,
      "atr_percent": 3.2675439750353834,
      "obv_trend": 48786400.0,
      "support_distance": 17.48725198014439,
      "resistance_distance": 4.655860868321651,
      "recent_high": 414.5,
      "recent_low": 326.79998779296875,
      "score": 10,
      "recommendation": "STRONG BUY",
      "signals": [
        "\ud83d\udcc8 Above key MAs",
        "Above 200-day MA",
        "RSI moderate 62.2",
        "\ud83d\ude80 MACD bullish",
        "Strong support level",
        "\ud83d\udcc8 Growth potential: 23.7% (confidence: 70%)"
      ],
      "buy_reasons": [
        "Weekly momentum +7.6%",
        "MACD bullish crossover"
      ],
      "sell_reasons": [],
      "growth_potential": 23.65586086832165,
      "growth_confidence": 0.7,
      "growth_factors": [
        "Resistance upside: +4.7%",
        "RSI momentum: +5%",
        "MACD bullish trend: +6%",
        "Good MA trend: +4%",
        "Momentum continuation: +4%"
      ],
      "has_recent_growth": "True",
      "meets_growth_requirement": "True",
      "market_cap": 2054125649920,
      "sector": "Technology",
      "pe_ratio": 33.909245,
      "forward_pe": 20.529562,
      "peg_ratio": 1.22,
      "price_to_book": 60.58415,
      "dividend_yield": 89.0,
      "ai_analysis": "Strong momentum with 16.0% recent growth. Healthy momentum with room to run.",
      "ai_score": 90
    },
    {
      "symbol": "AMAT",
      "company_name": "Applied Materials, Inc.",
      "current_price": 394.489990234375,
      "change_1d": 3.1103776916254495,
      "change_3d": -2.5613781288320343,
      "change_5d": -2.3322060217193035,
      "change_1w": 0.04057608286405387,
      "change_2w": -1.2515958152209452,
      "change_1m": 11.5008490235496,
      "change_3m": 20.274662071287125,
      "volume": "7039500",
      "volume_ratio": 1.267420391253818,
      "avg_volume": 5554195.0,
      "rsi": 47.4141512090232,
      "ma_5": 396.0179931640625,
      "ma_10": 397.03699645996096,
      "ma_20": 389.215998840332,
      "ma_50": 369.0625982666016,
      "ma_200": 361.783699773973,
      "macd": 8.821348542998692,
      "macd_signal": 10.549738647931246,
      "macd_histogram": -1.7283901049325543,
      "bb_upper": 425.3050144510423,
      "bb_lower": 353.1269832296217,
      "bb_position": 57.30692054742246,
      "bb_width": 18.544466680834,
      "stoch_k": 20.19077455595707,
      "stoch_d": 34.55017150429746,
      "williams_r": -59.88950990574191,
      "atr": 13.327144077845983,
      "atr_percent": 3.3783224942990415,
      "obv_trend": 13612200.0,
      "support_distance": 14.50987139125317,
      "resistance_distance": 6.593325663389303,
      "recent_high": 420.5,
      "recent_low": 337.25,
      "score": 8,
      "recommendation": "STRONG BUY",
      "signals": [
        "\ud83d\udcc8 Daily gain +3.1%",
        "\ud83d\udcc8 Above key MAs",
        "Above 200-day MA",
        "RSI neutral 47.4",
        "\ud83d\udcc9 MACD bearish",
        "Strong support level",
        "\u2728 Golden cross"
      ],
      "buy_reasons": [
        "Golden cross formation"
      ],
      "sell_reasons": [
        "MACD bearish crossover"
      ],
      "growth_potential": 15.593325663389303,
      "growth_confidence": 0.4,
      "growth_factors": [
        "Resistance upside: +6.6%",
        "RSI momentum: +5%",
        "Good MA trend: +4%"
      ],
      "has_recent_growth": "True",
      "meets_growth_requirement": "True",
      "market_cap": 313071140864,
      "sector": "Technology",
      "pe_ratio": 40.502052,
      "forward_pe": 28.035816,
      "peg_ratio": 1.82,
      "price_to_book": 14.415859,
      "dividend_yield": 54.0,
      "ai_analysis": "Strong momentum with 11.5% recent growth. High growth potential of 15.6%.",
      "ai_score": 86
    },
    {
      "symbol": "NVDA",
      "company_name": "NVIDIA Corporation",
      "current_price": 199.57000732421875,
      "change_1d": -4.626041900014934,
      "change_3d": -7.86666970043787,
      "change_5d": -0.035059139272526296,
      "change_1w": -0.15509183060881865,
      "change_2w": 5.799714869435959,
      "change_1m": 13.553346983908252,
      "change_3m": 7.526966585793423,
      "volume": "224690300",
      "volume_ratio": 1.5177327403810463,
      "avg_volume": 148043390.0,
      "rsi": 59.743508622011156,
      "ma_5": 209.3740020751953,
      "ma_10": 205.26300048828125,
      "ma_20": 196.1710006713867,
      "ma_50": 186.9403924560547,
      "ma_200": 186.38161394673008,
      "macd": 7.0349371491495845,
      "macd_signal": 6.346870088645622,
      "macd_histogram": 0.688067060503962,
      "bb_upper": 219.80975056410765,
      "bb_lower": 172.53225077866577,
      "bb_position": 57.189480552604635,
      "bb_width": 24.100147128595303,
      "stoch_k": 70.3581601280748,
      "stoch_d": 84.35178758803417,
      "williams_r": -55.51623203570626,
      "atr": 6.265713282993862,
      "atr_percent": 3.1396066808850027,
      "obv_trend": -121995400.0,
      "support_distance": 14.130385915764332,
      "resistance_distance": 8.648591408224775,
      "recent_high": 216.8300018310547,
      "recent_low": 171.3699951171875,
      "score": 7,
      "recommendation": "BUY",
      "signals": [
        "\ud83d\udcc9 Daily loss -4.6%",
        "\ud83d\udcc8 Above key MAs",
        "Above 200-day MA",
        "RSI moderate 59.7",
        "\ud83d\ude80 MACD bullish",
        "Volume above avg 1.5x",
        "Strong support level",
        "\ud83d\udcc8 Growth potential: 26.6% (confidence: 70%)"
      ],
      "buy_reasons": [
        "MACD bullish crossover"
      ],
      "sell_reasons": [],
      "growth_potential": 26.648591408224775,
      "growth_confidence": 0.7,
      "growth_factors": [
        "Resistance upside: +8.6%",
        "RSI momentum: +5%",
        "MACD bullish trend: +6%",
        "Good MA trend: +4%",
        "Volume support: +3%"
      ],
      "has_recent_growth": "True",
      "meets_growth_requirement": "True",
      "market_cap": 4850548998144,
      "sector": "Technology",
      "pe_ratio": 40.645622,
      "forward_pe": 17.756636,
      "peg_ratio": 0.76,
      "price_to_book": 30.835909,
      "dividend_yield": 2.0,
      "ai_analysis": "Strong momentum with 13.6% recent growth. Healthy momentum with room to run.",
      "ai_score": 85
    },
    {
      "symbol": "AVGO",
      "company_name": "Broadcom Inc.",
      "current_price": 417.42999267578125,
      "change_1d": 2.954736738947925,
      "change_3d": -0.1841270943982659,
      "change_5d": -0.597706755972889,
      "change_1w": 3.7944100103298553,
      "change_2w": 12.348272477505041,
      "change_1m": 33.15576435588818,
      "change_3m": 26.33434622382725,
      "volume": "21800300",
      "volume_ratio": 0.9939307230700912,
      "avg_volume": 21933420.0,
      "rsi": 70.6703855310766,
      "ma_5": 412.7340026855469,
      "ma_10": 411.4600036621094,
      "ma_20": 385.518000793457,
      "ma_50": 347.4287811279297,
      "ma_200": 343.80024817682084,
      "macd": 21.716908678716038,
      "macd_signal": 21.20266323358602,
      "macd_histogram": 0.5142454451300189,
      "bb_upper": 455.1075360532203,
      "bb_lower": 315.9284655336937,
      "bb_position": 72.92872898432458,
      "bb_width": 36.10183447545226,
      "stoch_k": 69.13978851616686,
      "stoch_d": 73.90115971788164,
      "williams_r": -19.856272019154208,
      "atr": 12.305001395089286,
      "atr_percent": 2.947800017007069,
      "obv_trend": 20837500.0,
      "support_distance": 27.712429558369116,
      "resistance_distance": 2.845987373034722,
      "recent_high": 429.30999755859375,
      "recent_low": 301.75,
      "score": 10,
      "recommendation": "STRONG BUY",
      "signals": [
        "\ud83d\udcc8 Daily gain +3.0%",
        "\ud83c\udfaf Perfect MA stack",
        "Above 200-day MA",
        "\u26a0\ufe0f RSI overbought 70.7",
        "\ud83d\ude80 MACD bullish",
        "Strong support level",
        "\ud83d\udcc8 Growth potential: 20.8% (confidence: 60%)"
      ],
      "buy_reasons": [
        "Perfect MA alignment (bullish)",
        "MACD bullish crossover",
        "Strong monthly trend +33.2%"
      ],
      "sell_reasons": [
        "Overbought RSI 70.7",
        "Williams %R overbought"
      ],
      "growth_potential": 20.845987373034724,
      "growth_confidence": 0.6,
      "growth_factors": [
        "Resistance upside: +2.8%",
        "MACD bullish trend: +6%",
        "Perfect MA alignment: +8%",
        "Momentum continuation: +4%"
      ],
      "has_recent_growth": "True",
      "meets_growth_requirement": "True",
      "market_cap": 1976392613888,
      "sector": "Technology",
      "pe_ratio": 81.37037,
      "forward_pe": 23.039581,
      "peg_ratio": 0.87,
      "price_to_book": 24.75126,
      "dividend_yield": 62.0,
      "ai_analysis": "Strong momentum with 33.2% recent growth. High growth potential of 20.8%.",
      "ai_score": 85
    },
    {
      "symbol": "ARM",
      "company_name": "Arm Holdings plc",
      "current_price": 210.32000732421875,
      "change_1d": 4.27884613929718,
      "change_3d": -2.575503720973102,
      "change_5d": 2.7906782155487218,
      "change_1w": 19.84728516770799,
      "change_2w": 41.22071957801193,
      "change_1m": 35.629069059424154,
      "change_3m": 96.68942927519896,
      "volume": "7696900",
      "volume_ratio": 0.8958753929035551,
      "avg_volume": 8591485.0,
      "rsi": 72.32850821090712,
      "ma_5": 212.27000122070314,
      "ma_10": 197.98500213623046,
      "ma_20": 175.4847511291504,
      "ma_50": 148.15250137329102,
      "ma_200": 142.51653326711346,
      "macd": 18.458682490483056,
      "macd_signal": 15.604061196976154,
      "macd_histogram": 2.854621293506902,
      "bb_upper": 230.53743710528195,
      "bb_lower": 120.43206515301884,
      "bb_position": 81.63810773026715,
      "bb_width": 62.74355534813937,
      "stoch_k": 62.50531216832122,
      "stoch_d": 68.13608792812899,
      "williams_r": -30.339307577821863,
      "atr": 14.113927568708148,
      "atr_percent": 6.71069183967402,
      "obv_trend": 52933700.0,
      "support_distance": 34.58539509321704,
      "resistance_distance": 13.008741155750208,
      "recent_high": 237.67999267578125,
      "recent_low": 137.5800018310547,
      "score": 13,
      "recommendation": "STRONG BUY",
      "signals": [
        "\ud83d\udcc8 Daily gain +4.3%",
        "\ud83d\udcc8 Above key MAs",
        "Above 200-day MA",
        "\u26a0\ufe0f RSI overbought 72.3",
        "\ud83d\ude80 MACD bullish",
        "High volatility 6.7%",
        "Strong support level",
        "\u2728 Golden cross"
      ],
      "buy_reasons": [
        "Weekly momentum +19.8%",
        "MACD bullish crossover",
        "Strong monthly trend +35.6%",
        "Golden cross formation"
      ],
      "sell_reasons": [
        "Overbought RSI 72.3"
      ],
      "growth_potential": 23.008741155750208,
      "growth_confidence": 0.44999999999999996,
      "growth_factors": [
        "Resistance upside: +13.0%",
        "MACD bullish trend: +6%",
        "Good MA trend: +4%"
      ],
      "has_recent_growth": "True",
      "meets_growth_requirement": "True",
      "market_cap": 223359549440,
      "sector": "Technology",
      "pe_ratio": 276.73685,
      "forward_pe": 98.092445,
      "peg_ratio": 2.39,
      "price_to_book": 28.642246,
      "dividend_yield": 0,
      "ai_analysis": "Strong momentum with 35.6% recent growth. High growth potential of 23.0%.",
      "ai_score": 85
    },
    {
      "symbol": "COP",
      "company_name": "ConocoPhillips",
      "current_price": 125.77999877929688,
      "change_1d": -1.925926877741228,
      "change_3d": 3.3694924916487663,
      "change_5d": 1.1337107032053946,
      "change_1w": 4.590052008159253,
      "change_2w": 2.6356553627949766,
      "change_1m": -2.0252422531756062,
      "change_3m": 24.529751314942384,
      "volume": "11943900",
      "volume_ratio": 1.3639252232926669,
      "avg_volume": 8757005.0,
      "rsi": 54.71256977655917,
      "ma_5": 124.35800018310547,
      "ma_10": 122.15100021362305,
      "ma_20": 123.47900085449218,
      "ma_50": 121.79140014648438,
      "ma_200": 118.97220599266791,
      "macd": 0.28105745558332274,
      "macd_signal": -0.11776735011373206,
      "macd_histogram": 0.3988248056970548,
      "bb_upper": 132.5038521369796,
      "bb_lower": 114.45414957200478,
      "bb_position": 62.748121009316485,
      "bb_width": 14.617629264950565,
      "stoch_k": 87.13004166715815,
      "stoch_d": 75.61864679101824,
      "williams_r": -15.556938689956498,
      "atr": 3.9600023542131697,
      "atr_percent": 3.1483561716053843,
      "obv_trend": 10574800.0,
      "support_distance": 10.788678507331813,
      "resistance_distance": 6.8611901467381635,
      "recent_high": 134.41000366210938,
      "recent_low": 112.20999908447266,
      "score": 9,
      "recommendation": "STRONG BUY",
      "signals": [
        "\ud83d\udcc8 Above key MAs",
        "Above 200-day MA",
        "RSI neutral 54.7",
        "\ud83d\ude80 MACD bullish",
        "Strong support level",
        "\u2728 Golden cross",
        "\ud83d\udcc8 Growth potential: 25.9% (confidence: 70%)"
      ],
      "buy_reasons": [
        "MACD bullish crossover",
        "Golden cross formation"
      ],
      "sell_reasons": [
        "Williams %R overbought"
      ],
      "growth_potential": 25.861190146738164,
      "growth_confidence": 0.7,
      "growth_factors": [
        "Resistance upside: +6.9%",
        "RSI momentum: +5%",
        "MACD bullish trend: +6%",
        "Good MA trend: +4%",
        "Momentum continuation: +4%"
      ],
      "has_recent_growth": "False",
      "meets_growth_requirement": true,
      "market_cap": 153237012480,
      "sector": "Energy",
      "pe_ratio": 21.318644,
      "forward_pe": 14.784723,
      "peg_ratio": 0,
      "price_to_book": 2.3896646,
      "dividend_yield": 267.0,
      "ai_analysis": "Strong momentum with 4.6% recent growth. Healthy momentum with room to run.",
      "ai_score": 85
    }
  ]
}